Workbook
Name brand: Ввод!$B$5
Name niche: Ввод!$B$6
Name mp_rev: Ввод!$B$7
Name mp_aov: Ввод!$B$8
Name mp_take: Ввод!$B$9
Name cogs: Ввод!$B$10
Name wordstat: Ввод!$B$11
Name followers: Ввод!$B$12
Name freq: Ввод!$B$13
Name stock: Ввод!$B$14
Name acq: Ввод!$B$33
Name ship: Ввод!$B$34
Name pick: Ввод!$B$35
Name crm_pct: Ввод!$B$36
Name brand_cost: Ввод!$B$37
Name platform: Ввод!$B$38
Name svc_setup: Ввод!$B$41
Name svc_month: Ввод!$B$42
Name svc_pct: Ввод!$B$43
Name conv_base_1: Ввод!$B$19
Name conv_base_2: Ввод!$C$19
Name conv_base_3: Ввод!$D$19
Name base_site_1: Ввод!$B$20
Name base_site_2: Ввод!$C$20
Name base_site_3: Ввод!$D$20
Name brand_share_1: Ввод!$B$21
Name brand_share_2: Ввод!$C$21
Name brand_share_3: Ввод!$D$21
Name brand_cr_1: Ввод!$B$22
Name brand_cr_2: Ввод!$C$22
Name brand_cr_3: Ввод!$D$22
Name social_cr_1: Ввод!$B$23
Name social_cr_2: Ввод!$C$23
Name social_cr_3: Ввод!$D$23
Name ads_budget_1: Ввод!$B$24
Name ads_budget_2: Ввод!$C$24
Name ads_budget_3: Ввод!$D$24
Name cpc_1: Ввод!$B$25
Name cpc_2: Ввод!$C$25
Name cpc_3: Ввод!$D$25
Name ads_cr_1: Ввод!$B$26
Name ads_cr_2: Ввод!$C$26
Name ads_cr_3: Ввод!$D$26
Name aov_k_1: Ввод!$B$27
Name aov_k_2: Ввод!$C$27
Name aov_k_3: Ввод!$D$27
Name incr_1: Ввод!$B$28
Name incr_2: Ввод!$C$28
Name incr_3: Ввод!$D$28
Name churn_1: Ввод!$B$29
Name churn_2: Ввод!$C$29
Name churn_3: Ввод!$D$29
Name ramp_1: Ввод!$B$30
Name ramp_2: Ввод!$C$30
Name ramp_3: Ввод!$D$30

Sheet КП
A1: ="Свой интернет-магазин для "&Ввод!$B$5
A2: ="Расчёт на ваших цифрах. Ниша: "&Ввод!$B$6
A4: Сколько вы сейчас отдаёте маркетплейсам
A5: Оборот на маркетплейсах, ₽/мес | B5: =mp_rev
A6: Удерживает маркетплейс, ₽/мес | B6: =mp_rev*mp_take
A7: Удерживает маркетплейс, ₽/год | B7: =mp_rev*mp_take*12
A8: Товар на складах маркетплейсов, ₽ | B8: =stock
A9: Ваш бренд ищут в Яндексе, раз в мес | B9: =wordstat
A11: Что даст свой магазин
A12: Показатель | B12: Осторожный | C12: Базовый | D12: Сильный
A13: Выручка сайта на 12-й месяц, ₽/мес | B13: =Расчёт!M16 | C13: =Расчёт!M41 | D13: =Расчёт!M66
A14: Выручка сайта на 24-й месяц, ₽/мес | B14: =Расчёт!Y16 | C14: =Расчёт!Y41 | D14: =Расчёт!Y66
A15: Доля сайта в обороте на 24-й месяц | B15: =Расчёт!Y19 | C15: =Расчёт!Y44 | D15: =Расчёт!Y69
A16: Прирост общего оборота на 24-й месяц | B16: =Расчёт!Y17/mp_rev | C16: =Расчёт!Y42/mp_rev | D16: =Расчёт!Y67/mp_rev
A17: Выручка сайта за 2-й год, ₽ | B17: =SUM(Расчёт!N16:Y16) | C17: =SUM(Расчёт!N41:Y41) | D17: =SUM(Расчёт!N66:Y66)
A18: Покупателей в своей базе через 24 мес | B18: =Расчёт!Y9 | C18: =Расчёт!Y34 | D18: =Расчёт!Y59
A19: Расходы сайта на 24-й месяц, % выручки | B19: =Расчёт!Y21 | C19: =Расчёт!Y46 | D19: =Расчёт!Y71
A20: Чистый эффект за 1-й год, ₽ | B20: =SUM(Расчёт!B25:M25) | C20: =SUM(Расчёт!B50:M50) | D20: =SUM(Расчёт!B75:M75)
A21: Чистый эффект за 2-й год, ₽ | B21: =SUM(Расчёт!N25:Y25) | C21: =SUM(Расчёт!N50:Y50) | D21: =SUM(Расчёт!N75:Y75)
A22: Окупаемость вложений, мес | B22: =IFERROR(MATCH(1,Расчёт!B27:Y27,0),"больше 24") | C22: =IFERROR(MATCH(1,Расчёт!B52:Y52,0),"больше 24") | D22: =IFERROR(MATCH(1,Расчёт!B77:Y77,0),"больше 24")
A24: Чистый эффект = маржа сайта после себестоимости, всех расходов и наших услуг минус маржа, которую перешедшие с МП заказы и так дали бы на маркетплейсе.
A25: Источники рыночных цифр — лист «Справка». Допущения сценариев — лист «Ввод», раздел 2.
A26: Маркетплейсы остаются главным каналом: сайт — второй канал со своей базой покупателей и страховка от изменения условий и потерь на складах.

Sheet Ввод
A1: Калькулятор КП: свой интернет-магазин для селлера
A2: Жёлтые ячейки с синим шрифтом — вводные, меняй их. Остальное считается само. На каждого селлера: Файл → Создать копию.
A4: 1. Профиль селлера (из профилирования)
A5: Бренд | B5: Пример бренда
A6: Ниша | B6: Одежда
A7: Оборот на маркетплейсах, ₽/мес | B7: 3000000 | C7: MPStats / Moneyplace
A8: Средний чек на маркетплейсе, ₽ | B8: 2500 | C8: MPStats / Moneyplace
A9: Удержания маркетплейса, % выручки | B9: 0.42 | C9: Комиссия + логистика + хранение + реклама + возвраты. Рынок: 40–50% (Финансист, RB.ru 25.09.2026)
A10: Себестоимость товара, % от цены | B10: 0.35 | C10: Спроси у селлера или возьми типовое для ниши
A11: Запросы бренда в Вордстате, в мес | B11: 3000 | C11: wordstat.yandex.ru: название бренда, латиница + кириллица
A12: Подписчики в соцсетях и Telegram | B12: 5000 | C12: Все свои каналы бренда вместе
A13: Покупок одного клиента в год (в нише) | B13: 2 | C13: Одежда 2–3, косметика 4–6, расходники 6+
A14: Товар на складах маркетплейсов, ₽ | B14: 6000000 | C14: Остатки по себестоимости или по цене
A17: 2. Допущения по сценариям
A18: Показатель | B18: Осторожный | C18: Базовый | D18: Сильный | E18: Откуда цифра
A19: Покупатели МП, перешедшие в базу (QR, Telegram, гарантия), % от заказов | B19: 0.01 | C19: 0.03 | D19: 0.05 | E19: QR на гарантию/инструкцию в Telegram-боте, адрес сайта в чате WB (разрешено). По рынку 1–5% заказов (не проверено). Нельзя: «бонус за отзыв» (штраф WB 50 000 ₽), контакты во вкладышах Ozon
A20: Доля повторных покупок базы, сделанных на сайте | B20: 0.2 | C20: 0.35 | D20: 0.45 | E20: Зависит от выгоды на сайте: бонусы, наборы, эксклюзивы
A21: Доля брендового поиска, которую забирает сайт | B21: 0.1 | C21: 0.2 | D21: 0.3 | E21: Остальное уходит на WB/Ozon. 7 из 10 проверяют товар на МП (Я.Маркет, 2025)
A22: Конверсия брендового трафика | B22: 0.02 | C22: 0.03 | D22: 0.04 | E22: Брендовый трафик 3–6%, холодный 0,8–2% (оценка)
A23: Покупают на сайте в месяц, % подписчиков | B23: 0.002 | C23: 0.004 | D23: 0.007 | E23: Оценка
A24: Бюджет на Директ / VK, ₽/мес | B24: 30000 | C24: 60000 | D24: 100000 | E24: Холодная реклама на старте обычно в минус, окупается позже
A25: Цена клика, ₽ | B25: 45 | C25: 45 | D25: 45 | E25: Директ на поиске 44 ₽ (click.ru, 2 кв. 2026), товарные 50–150 ₽
A26: Конверсия рекламного трафика | B26: 0.008 | C26: 0.012 | D26: 0.018 | E26: Холодный трафик нового сайта 0,8–2% (оценка)
A27: Средний чек на сайте, % от чека МП | B27: 1 | C27: 1.1 | D27: 1.2 | E27: На сайте чек выше за счёт наборов и бесплатной доставки от суммы
A28: Новые покупатели (не ушли бы на МП), % выручки сайта | B28: 0.2 | C28: 0.3 | D28: 0.4 | E28: Остальное — каннибализация: эти деньги селлер получил бы на МП
A29: Отток базы в месяц (перестают покупать) | B29: 0.06 | C29: 0.05 | D29: 0.04 | E29: Без оттока база растёт бесконечно; 4–6% в месяц — около половины за год
A30: Месяцев до выхода на полную мощность | B30: 9 | C30: 6 | D30: 4 | E30: Разгон: SEO, база, оптимизация рекламы
A32: 3. Расходы своего сайта
A33: Эквайринг, % от выручки сайта | B33: 0.02 | C33: СБП 0,4–0,7%, карты около 2,8% (ЮKassa)
A34: Доставка до ПВЗ, ₽/заказ (за счёт продавца) | B34: 250 | C34: Яндекс от 99 ₽, Ozon от 123 ₽, СДЭК от 250 ₽
A35: Сборка и упаковка, ₽/заказ | B35: 70 | C35: Фулфилмент 50–75 ₽
A36: Бонусы и рассылки, % от выручки базы | B36: 0.07 | C36: Бонусы за покупку на сайте + сервис рассылок
A37: Брендовая реклама и SEO, % от выручки бренд-трафика | B37: 0.05 | C37: Защита бренда в Директе
A38: Платформа, CRM, сервисы, ₽/мес | B38: 15000 | C38: InSales/Битрикс + CRM + бот
A40: 4. Наши услуги (для КП)
A41: Запуск под ключ, ₽ (разово) | B41: 200000 | C41: Подставь свою цену
A42: Сопровождение, ₽/мес | B42: 50000 | C42: Подставь свою цену
A43: Процент с продаж сайта | B43: 0 | C43: Если работаешь за результат

Sheet Расчёт
A1: Помесячный расчёт по трём сценариям (24 месяца)
A2: Ничего не вводить: всё считается из листа «Ввод».
A4: Сценарий: Осторожный
A5: Месяц | B5: 1 | C5: 2 | D5: 3 | E5: 4 | F5: 5 | G5: 6 | H5: 7 | I5: 8 | J5: 9 | K5: 10 | L5: 11 | M5: 12 | N5: 13 | O5: 14 | P5: 15 | Q5: 16 | R5: 17 | S5: 18 | T5: 19 | U5: 20 | V5: 21 | W5: 22 | X5: 23 | Y5: 24
A6: Разгон (доля полной мощности) | B6: =MIN(1,B5/ramp_1) | C6: =MIN(1,C5/ramp_1) | D6: =MIN(1,D5/ramp_1) | E6: =MIN(1,E5/ramp_1) | F6: =MIN(1,F5/ramp_1) | G6: =MIN(1,G5/ramp_1) | H6: =MIN(1,H5/ramp_1) | I6: =MIN(1,I5/ramp_1) | ... Y6: =MIN(1,Y5/ramp_1)
A7: Заказов на МП в месяц | B7: =mp_rev/mp_aov | C7: =mp_rev/mp_aov | D7: =mp_rev/mp_aov | E7: =mp_rev/mp_aov | F7: =mp_rev/mp_aov | G7: =mp_rev/mp_aov | H7: =mp_rev/mp_aov | I7: =mp_rev/mp_aov | ... Y7: =mp_rev/mp_aov
A8: Новых людей в базе (с МП + новые покупатели сайта) | B8: =B7*conv_base_1*B6+B11+B12+B13 | C8: =C7*conv_base_1*C6+C11+C12+C13 | D8: =D7*conv_base_1*D6+D11+D12+D13 | E8: =E7*conv_base_1*E6+E11+E12+E13 | F8: =F7*conv_base_1*F6+F11+F12+F13 | G8: =G7*conv_base_1*G6+G11+G12+G13 | H8: =H7*conv_base_1*H6+H11+H12+H13 | I8: =I7*conv_base_1*I6+I11+I12+I13 | ... Y8: =Y7*conv_base_1*Y6+Y11+Y12+Y13
A9: База на конец месяца | B9: =B8 | C9: =B9*(1-churn_1)+C8 | D9: =C9*(1-churn_1)+D8 | E9: =D9*(1-churn_1)+E8 | F9: =E9*(1-churn_1)+F8 | G9: =F9*(1-churn_1)+G8 | H9: =G9*(1-churn_1)+H8 | I9: =H9*(1-churn_1)+I8 | J9: =I9*(1-churn_1)+J8 | ... Y9: =X9*(1-churn_1)+Y8
A10: Заказы сайта: повторные из базы | B10: =0*freq/12*base_site_1 | C10: =B9*freq/12*base_site_1 | D10: =C9*freq/12*base_site_1 | E10: =D9*freq/12*base_site_1 | F10: =E9*freq/12*base_site_1 | G10: =F9*freq/12*base_site_1 | H10: =G9*freq/12*base_site_1 | I10: =H9*freq/12*base_site_1 | J10: =I9*freq/12*base_site_1 | ... Y10: =X9*freq/12*base_site_1
A11: Заказы сайта: брендовый поиск | B11: =wordstat*brand_share_1*B6*brand_cr_1 | C11: =wordstat*brand_share_1*C6*brand_cr_1 | D11: =wordstat*brand_share_1*D6*brand_cr_1 | E11: =wordstat*brand_share_1*E6*brand_cr_1 | F11: =wordstat*brand_share_1*F6*brand_cr_1 | G11: =wordstat*brand_share_1*G6*brand_cr_1 | H11: =wordstat*brand_share_1*H6*brand_cr_1 | I11: =wordstat*brand_share_1*I6*brand_cr_1 | ... Y11: =wordstat*brand_share_1*Y6*brand_cr_1
A12: Заказы сайта: соцсети и Telegram | B12: =followers*social_cr_1*B6 | C12: =followers*social_cr_1*C6 | D12: =followers*social_cr_1*D6 | E12: =followers*social_cr_1*E6 | F12: =followers*social_cr_1*F6 | G12: =followers*social_cr_1*G6 | H12: =followers*social_cr_1*H6 | I12: =followers*social_cr_1*I6 | ... Y12: =followers*social_cr_1*Y6
A13: Заказы сайта: Директ / VK | B13: =ads_budget_1/cpc_1*ads_cr_1*(0.5+0.5*B6) | C13: =ads_budget_1/cpc_1*ads_cr_1*(0.5+0.5*C6) | D13: =ads_budget_1/cpc_1*ads_cr_1*(0.5+0.5*D6) | E13: =ads_budget_1/cpc_1*ads_cr_1*(0.5+0.5*E6) | F13: =ads_budget_1/cpc_1*ads_cr_1*(0.5+0.5*F6) | G13: =ads_budget_1/cpc_1*ads_cr_1*(0.5+0.5*G6) | H13: =ads_budget_1/cpc_1*ads_cr_1*(0.5+0.5*H6) | I13: =ads_budget_1/cpc_1*ads_cr_1*(0.5+0.5*I6) | ... Y13: =ads_budget_1/cpc_1*ads_cr_1*(0.5+0.5*Y6)
A14: Заказов на сайте всего | B14: =B10+B11+B12+B13 | C14: =C10+C11+C12+C13 | D14: =D10+D11+D12+D13 | E14: =E10+E11+E12+E13 | F14: =F10+F11+F12+F13 | G14: =G10+G11+G12+G13 | H14: =H10+H11+H12+H13 | I14: =I10+I11+I12+I13 | ... Y14: =Y10+Y11+Y12+Y13
A15: Средний чек сайта, ₽ | B15: =mp_aov*aov_k_1 | C15: =mp_aov*aov_k_1 | D15: =mp_aov*aov_k_1 | E15: =mp_aov*aov_k_1 | F15: =mp_aov*aov_k_1 | G15: =mp_aov*aov_k_1 | H15: =mp_aov*aov_k_1 | I15: =mp_aov*aov_k_1 | ... Y15: =mp_aov*aov_k_1
A16: Выручка сайта, ₽ | B16: =B14*B15 | C16: =C14*C15 | D16: =D14*D15 | E16: =E14*E15 | F16: =F14*F15 | G16: =G14*G15 | H16: =H14*H15 | I16: =I14*I15 | ... Y16: =Y14*Y15
A17: в т.ч. новые деньги (прирост оборота), ₽ | B17: =B16*incr_1 | C17: =C16*incr_1 | D17: =D16*incr_1 | E17: =E16*incr_1 | F17: =F16*incr_1 | G17: =G16*incr_1 | H17: =H16*incr_1 | I17: =I16*incr_1 | ... Y17: =Y16*incr_1
A18: в т.ч. перешло с МП, ₽ | B18: =B16-B17 | C18: =C16-C17 | D18: =D16-D17 | E18: =E16-E17 | F18: =F16-F17 | G18: =G16-G17 | H18: =H16-H17 | I18: =I16-I17 | ... Y18: =Y16-Y17
A19: Доля сайта в общем обороте | B19: =B16/(mp_rev-B18+B16) | C19: =C16/(mp_rev-C18+C16) | D19: =D16/(mp_rev-D18+D16) | E19: =E16/(mp_rev-E18+E16) | F19: =F16/(mp_rev-F18+F16) | G19: =G16/(mp_rev-G18+G16) | H19: =H16/(mp_rev-H18+H16) | I19: =I16/(mp_rev-I18+I16) | ... Y19: =Y16/(mp_rev-Y18+Y16)
A20: Расходы сайта (без себестоимости), ₽ | B20: =B16*acq+B14*(ship+pick)+B10*B15*crm_pct+B11*B15*brand_cost+ads_budget_1+platform | C20: =C16*acq+C14*(ship+pick)+C10*C15*crm_pct+C11*C15*brand_cost+ads_budget_1+platform | D20: =D16*acq+D14*(ship+pick)+D10*D15*crm_pct+D11*D15*brand_cost+ads_budget_1+platform | E20: =E16*acq+E14*(ship+pick)+E10*E15*crm_pct+E11*E15*brand_cost+ads_budget_1+platform | F20: =F16*acq+F14*(ship+pick)+F10*F15*crm_pct+F11*F15*brand_cost+ads_budget_1+platform | G20: =G16*acq+G14*(ship+pick)+G10*G15*crm_pct+G11*G15*brand_cost+ads_budget_1+platform | H20: =H16*acq+H14*(ship+pick)+H10*H15*crm_pct+H11*H15*brand_cost+ads_budget_1+platform | I20: =I16*acq+I14*(ship+pick)+I10*I15*crm_pct+I11*I15*brand_cost+ads_budget_1+platform | ... Y20: =Y16*acq+Y14*(ship+pick)+Y10*Y15*crm_pct+Y11*Y15*brand_cost+ads_budget_1+platform
A21: Расходы сайта, % выручки | B21: =IF(B16=0,0,B20/B16) | C21: =IF(C16=0,0,C20/C16) | D21: =IF(D16=0,0,D20/D16) | E21: =IF(E16=0,0,E20/E16) | F21: =IF(F16=0,0,F20/F16) | G21: =IF(G16=0,0,G20/G16) | H21: =IF(H16=0,0,H20/H16) | I21: =IF(I16=0,0,I20/I16) | ... Y21: =IF(Y16=0,0,Y20/Y16)
A22: Наши услуги, ₽ | B22: =svc_setup+svc_month+B16*svc_pct | C22: =svc_month+C16*svc_pct | D22: =svc_month+D16*svc_pct | E22: =svc_month+E16*svc_pct | F22: =svc_month+F16*svc_pct | G22: =svc_month+G16*svc_pct | H22: =svc_month+H16*svc_pct | I22: =svc_month+I16*svc_pct | J22: =svc_month+J16*svc_pct | ... Y22: =svc_month+Y16*svc_pct
A23: Маржа сайта после себестоимости и расходов, ₽ | B23: =B16*(1-cogs)-B20-B22 | C23: =C16*(1-cogs)-C20-C22 | D23: =D16*(1-cogs)-D20-D22 | E23: =E16*(1-cogs)-E20-E22 | F23: =F16*(1-cogs)-F20-F22 | G23: =G16*(1-cogs)-G20-G22 | H23: =H16*(1-cogs)-H20-H22 | I23: =I16*(1-cogs)-I20-I22 | ... Y23: =Y16*(1-cogs)-Y20-Y22
A24: Маржа, которую эти заказы дали бы на МП, ₽ | B24: =B18*(1-cogs-mp_take) | C24: =C18*(1-cogs-mp_take) | D24: =D18*(1-cogs-mp_take) | E24: =E18*(1-cogs-mp_take) | F24: =F18*(1-cogs-mp_take) | G24: =G18*(1-cogs-mp_take) | H24: =H18*(1-cogs-mp_take) | I24: =I18*(1-cogs-mp_take) | ... Y24: =Y18*(1-cogs-mp_take)
A25: Чистый эффект для селлера, ₽ | B25: =B23-B24 | C25: =C23-C24 | D25: =D23-D24 | E25: =E23-E24 | F25: =F23-F24 | G25: =G23-G24 | H25: =H23-H24 | I25: =I23-I24 | ... Y25: =Y23-Y24
A26: Нарастающим итогом, ₽ | B26: =B25 | C26: =B26+C25 | D26: =C26+D25 | E26: =D26+E25 | F26: =E26+F25 | G26: =F26+G25 | H26: =G26+H25 | I26: =H26+I25 | J26: =I26+J25 | ... Y26: =X26+Y25
A27: Окупилось (1 = да) | B27: =IF(B26>0,1,0) | C27: =IF(C26>0,1,0) | D27: =IF(D26>0,1,0) | E27: =IF(E26>0,1,0) | F27: =IF(F26>0,1,0) | G27: =IF(G26>0,1,0) | H27: =IF(H26>0,1,0) | I27: =IF(I26>0,1,0) | ... Y27: =IF(Y26>0,1,0)
A29: Сценарий: Базовый
A30: Месяц | B30: 1 | C30: 2 | D30: 3 | E30: 4 | F30: 5 | G30: 6 | H30: 7 | I30: 8 | J30: 9 | K30: 10 | L30: 11 | M30: 12 | N30: 13 | O30: 14 | P30: 15 | Q30: 16 | R30: 17 | S30: 18 | T30: 19 | U30: 20 | V30: 21 | W30: 22 | X30: 23 | Y30: 24
A31: Разгон (доля полной мощности) | B31: =MIN(1,B30/ramp_2) | C31: =MIN(1,C30/ramp_2) | D31: =MIN(1,D30/ramp_2) | E31: =MIN(1,E30/ramp_2) | F31: =MIN(1,F30/ramp_2) | G31: =MIN(1,G30/ramp_2) | H31: =MIN(1,H30/ramp_2) | I31: =MIN(1,I30/ramp_2) | ... Y31: =MIN(1,Y30/ramp_2)
A32: Заказов на МП в месяц | B32: =mp_rev/mp_aov | C32: =mp_rev/mp_aov | D32: =mp_rev/mp_aov | E32: =mp_rev/mp_aov | F32: =mp_rev/mp_aov | G32: =mp_rev/mp_aov | H32: =mp_rev/mp_aov | I32: =mp_rev/mp_aov | ... Y32: =mp_rev/mp_aov
A33: Новых людей в базе (с МП + новые покупатели сайта) | B33: =B32*conv_base_2*B31+B36+B37+B38 | C33: =C32*conv_base_2*C31+C36+C37+C38 | D33: =D32*conv_base_2*D31+D36+D37+D38 | E33: =E32*conv_base_2*E31+E36+E37+E38 | F33: =F32*conv_base_2*F31+F36+F37+F38 | G33: =G32*conv_base_2*G31+G36+G37+G38 | H33: =H32*conv_base_2*H31+H36+H37+H38 | I33: =I32*conv_base_2*I31+I36+I37+I38 | ... Y33: =Y32*conv_base_2*Y31+Y36+Y37+Y38
A34: База на конец месяца | B34: =B33 | C34: =B34*(1-churn_2)+C33 | D34: =C34*(1-churn_2)+D33 | E34: =D34*(1-churn_2)+E33 | F34: =E34*(1-churn_2)+F33 | G34: =F34*(1-churn_2)+G33 | H34: =G34*(1-churn_2)+H33 | I34: =H34*(1-churn_2)+I33 | J34: =I34*(1-churn_2)+J33 | ... Y34: =X34*(1-churn_2)+Y33
A35: Заказы сайта: повторные из базы | B35: =0*freq/12*base_site_2 | C35: =B34*freq/12*base_site_2 | D35: =C34*freq/12*base_site_2 | E35: =D34*freq/12*base_site_2 | F35: =E34*freq/12*base_site_2 | G35: =F34*freq/12*base_site_2 | H35: =G34*freq/12*base_site_2 | I35: =H34*freq/12*base_site_2 | J35: =I34*freq/12*base_site_2 | ... Y35: =X34*freq/12*base_site_2
A36: Заказы сайта: брендовый поиск | B36: =wordstat*brand_share_2*B31*brand_cr_2 | C36: =wordstat*brand_share_2*C31*brand_cr_2 | D36: =wordstat*brand_share_2*D31*brand_cr_2 | E36: =wordstat*brand_share_2*E31*brand_cr_2 | F36: =wordstat*brand_share_2*F31*brand_cr_2 | G36: =wordstat*brand_share_2*G31*brand_cr_2 | H36: =wordstat*brand_share_2*H31*brand_cr_2 | I36: =wordstat*brand_share_2*I31*brand_cr_2 | ... Y36: =wordstat*brand_share_2*Y31*brand_cr_2
A37: Заказы сайта: соцсети и Telegram | B37: =followers*social_cr_2*B31 | C37: =followers*social_cr_2*C31 | D37: =followers*social_cr_2*D31 | E37: =followers*social_cr_2*E31 | F37: =followers*social_cr_2*F31 | G37: =followers*social_cr_2*G31 | H37: =followers*social_cr_2*H31 | I37: =followers*social_cr_2*I31 | ... Y37: =followers*social_cr_2*Y31
A38: Заказы сайта: Директ / VK | B38: =ads_budget_2/cpc_2*ads_cr_2*(0.5+0.5*B31) | C38: =ads_budget_2/cpc_2*ads_cr_2*(0.5+0.5*C31) | D38: =ads_budget_2/cpc_2*ads_cr_2*(0.5+0.5*D31) | E38: =ads_budget_2/cpc_2*ads_cr_2*(0.5+0.5*E31) | F38: =ads_budget_2/cpc_2*ads_cr_2*(0.5+0.5*F31) | G38: =ads_budget_2/cpc_2*ads_cr_2*(0.5+0.5*G31) | H38: =ads_budget_2/cpc_2*ads_cr_2*(0.5+0.5*H31) | I38: =ads_budget_2/cpc_2*ads_cr_2*(0.5+0.5*I31) | ... Y38: =ads_budget_2/cpc_2*ads_cr_2*(0.5+0.5*Y31)
A39: Заказов на сайте всего | B39: =B35+B36+B37+B38 | C39: =C35+C36+C37+C38 | D39: =D35+D36+D37+D38 | E39: =E35+E36+E37+E38 | F39: =F35+F36+F37+F38 | G39: =G35+G36+G37+G38 | H39: =H35+H36+H37+H38 | I39: =I35+I36+I37+I38 | ... Y39: =Y35+Y36+Y37+Y38
A40: Средний чек сайта, ₽ | B40: =mp_aov*aov_k_2 | C40: =mp_aov*aov_k_2 | D40: =mp_aov*aov_k_2 | E40: =mp_aov*aov_k_2 | F40: =mp_aov*aov_k_2 | G40: =mp_aov*aov_k_2 | H40: =mp_aov*aov_k_2 | I40: =mp_aov*aov_k_2 | ... Y40: =mp_aov*aov_k_2
A41: Выручка сайта, ₽ | B41: =B39*B40 | C41: =C39*C40 | D41: =D39*D40 | E41: =E39*E40 | F41: =F39*F40 | G41: =G39*G40 | H41: =H39*H40 | I41: =I39*I40 | ... Y41: =Y39*Y40
A42: в т.ч. новые деньги (прирост оборота), ₽ | B42: =B41*incr_2 | C42: =C41*incr_2 | D42: =D41*incr_2 | E42: =E41*incr_2 | F42: =F41*incr_2 | G42: =G41*incr_2 | H42: =H41*incr_2 | I42: =I41*incr_2 | ... Y42: =Y41*incr_2
A43: в т.ч. перешло с МП, ₽ | B43: =B41-B42 | C43: =C41-C42 | D43: =D41-D42 | E43: =E41-E42 | F43: =F41-F42 | G43: =G41-G42 | H43: =H41-H42 | I43: =I41-I42 | ... Y43: =Y41-Y42
A44: Доля сайта в общем обороте | B44: =B41/(mp_rev-B43+B41) | C44: =C41/(mp_rev-C43+C41) | D44: =D41/(mp_rev-D43+D41) | E44: =E41/(mp_rev-E43+E41) | F44: =F41/(mp_rev-F43+F41) | G44: =G41/(mp_rev-G43+G41) | H44: =H41/(mp_rev-H43+H41) | I44: =I41/(mp_rev-I43+I41) | ... Y44: =Y41/(mp_rev-Y43+Y41)
A45: Расходы сайта (без себестоимости), ₽ | B45: =B41*acq+B39*(ship+pick)+B35*B40*crm_pct+B36*B40*brand_cost+ads_budget_2+platform | C45: =C41*acq+C39*(ship+pick)+C35*C40*crm_pct+C36*C40*brand_cost+ads_budget_2+platform | D45: =D41*acq+D39*(ship+pick)+D35*D40*crm_pct+D36*D40*brand_cost+ads_budget_2+platform | E45: =E41*acq+E39*(ship+pick)+E35*E40*crm_pct+E36*E40*brand_cost+ads_budget_2+platform | F45: =F41*acq+F39*(ship+pick)+F35*F40*crm_pct+F36*F40*brand_cost+ads_budget_2+platform | G45: =G41*acq+G39*(ship+pick)+G35*G40*crm_pct+G36*G40*brand_cost+ads_budget_2+platform | H45: =H41*acq+H39*(ship+pick)+H35*H40*crm_pct+H36*H40*brand_cost+ads_budget_2+platform | I45: =I41*acq+I39*(ship+pick)+I35*I40*crm_pct+I36*I40*brand_cost+ads_budget_2+platform | ... Y45: =Y41*acq+Y39*(ship+pick)+Y35*Y40*crm_pct+Y36*Y40*brand_cost+ads_budget_2+platform
A46: Расходы сайта, % выручки | B46: =IF(B41=0,0,B45/B41) | C46: =IF(C41=0,0,C45/C41) | D46: =IF(D41=0,0,D45/D41) | E46: =IF(E41=0,0,E45/E41) | F46: =IF(F41=0,0,F45/F41) | G46: =IF(G41=0,0,G45/G41) | H46: =IF(H41=0,0,H45/H41) | I46: =IF(I41=0,0,I45/I41) | ... Y46: =IF(Y41=0,0,Y45/Y41)
A47: Наши услуги, ₽ | B47: =svc_setup+svc_month+B41*svc_pct | C47: =svc_month+C41*svc_pct | D47: =svc_month+D41*svc_pct | E47: =svc_month+E41*svc_pct | F47: =svc_month+F41*svc_pct | G47: =svc_month+G41*svc_pct | H47: =svc_month+H41*svc_pct | I47: =svc_month+I41*svc_pct | J47: =svc_month+J41*svc_pct | ... Y47: =svc_month+Y41*svc_pct
A48: Маржа сайта после себестоимости и расходов, ₽ | B48: =B41*(1-cogs)-B45-B47 | C48: =C41*(1-cogs)-C45-C47 | D48: =D41*(1-cogs)-D45-D47 | E48: =E41*(1-cogs)-E45-E47 | F48: =F41*(1-cogs)-F45-F47 | G48: =G41*(1-cogs)-G45-G47 | H48: =H41*(1-cogs)-H45-H47 | I48: =I41*(1-cogs)-I45-I47 | ... Y48: =Y41*(1-cogs)-Y45-Y47
A49: Маржа, которую эти заказы дали бы на МП, ₽ | B49: =B43*(1-cogs-mp_take) | C49: =C43*(1-cogs-mp_take) | D49: =D43*(1-cogs-mp_take) | E49: =E43*(1-cogs-mp_take) | F49: =F43*(1-cogs-mp_take) | G49: =G43*(1-cogs-mp_take) | H49: =H43*(1-cogs-mp_take) | I49: =I43*(1-cogs-mp_take) | ... Y49: =Y43*(1-cogs-mp_take)
A50: Чистый эффект для селлера, ₽ | B50: =B48-B49 | C50: =C48-C49 | D50: =D48-D49 | E50: =E48-E49 | F50: =F48-F49 | G50: =G48-G49 | H50: =H48-H49 | I50: =I48-I49 | ... Y50: =Y48-Y49
A51: Нарастающим итогом, ₽ | B51: =B50 | C51: =B51+C50 | D51: =C51+D50 | E51: =D51+E50 | F51: =E51+F50 | G51: =F51+G50 | H51: =G51+H50 | I51: =H51+I50 | J51: =I51+J50 | ... Y51: =X51+Y50
A52: Окупилось (1 = да) | B52: =IF(B51>0,1,0) | C52: =IF(C51>0,1,0) | D52: =IF(D51>0,1,0) | E52: =IF(E51>0,1,0) | F52: =IF(F51>0,1,0) | G52: =IF(G51>0,1,0) | H52: =IF(H51>0,1,0) | I52: =IF(I51>0,1,0) | ... Y52: =IF(Y51>0,1,0)
A54: Сценарий: Сильный
A55: Месяц | B55: 1 | C55: 2 | D55: 3 | E55: 4 | F55: 5 | G55: 6 | H55: 7 | I55: 8 | J55: 9 | K55: 10 | L55: 11 | M55: 12 | N55: 13 | O55: 14 | P55: 15 | Q55: 16 | R55: 17 | S55: 18 | T55: 19 | U55: 20 | V55: 21 | W55: 22 | X55: 23 | Y55: 24
A56: Разгон (доля полной мощности) | B56: =MIN(1,B55/ramp_3) | C56: =MIN(1,C55/ramp_3) | D56: =MIN(1,D55/ramp_3) | E56: =MIN(1,E55/ramp_3) | F56: =MIN(1,F55/ramp_3) | G56: =MIN(1,G55/ramp_3) | H56: =MIN(1,H55/ramp_3) | I56: =MIN(1,I55/ramp_3) | ... Y56: =MIN(1,Y55/ramp_3)
A57: Заказов на МП в месяц | B57: =mp_rev/mp_aov | C57: =mp_rev/mp_aov | D57: =mp_rev/mp_aov | E57: =mp_rev/mp_aov | F57: =mp_rev/mp_aov | G57: =mp_rev/mp_aov | H57: =mp_rev/mp_aov | I57: =mp_rev/mp_aov | ... Y57: =mp_rev/mp_aov
A58: Новых людей в базе (с МП + новые покупатели сайта) | B58: =B57*conv_base_3*B56+B61+B62+B63 | C58: =C57*conv_base_3*C56+C61+C62+C63 | D58: =D57*conv_base_3*D56+D61+D62+D63 | E58: =E57*conv_base_3*E56+E61+E62+E63 | F58: =F57*conv_base_3*F56+F61+F62+F63 | G58: =G57*conv_base_3*G56+G61+G62+G63 | H58: =H57*conv_base_3*H56+H61+H62+H63 | I58: =I57*conv_base_3*I56+I61+I62+I63 | ... Y58: =Y57*conv_base_3*Y56+Y61+Y62+Y63
A59: База на конец месяца | B59: =B58 | C59: =B59*(1-churn_3)+C58 | D59: =C59*(1-churn_3)+D58 | E59: =D59*(1-churn_3)+E58 | F59: =E59*(1-churn_3)+F58 | G59: =F59*(1-churn_3)+G58 | H59: =G59*(1-churn_3)+H58 | I59: =H59*(1-churn_3)+I58 | J59: =I59*(1-churn_3)+J58 | ... Y59: =X59*(1-churn_3)+Y58
A60: Заказы сайта: повторные из базы | B60: =0*freq/12*base_site_3 | C60: =B59*freq/12*base_site_3 | D60: =C59*freq/12*base_site_3 | E60: =D59*freq/12*base_site_3 | F60: =E59*freq/12*base_site_3 | G60: =F59*freq/12*base_site_3 | H60: =G59*freq/12*base_site_3 | I60: =H59*freq/12*base_site_3 | J60: =I59*freq/12*base_site_3 | ... Y60: =X59*freq/12*base_site_3
A61: Заказы сайта: брендовый поиск | B61: =wordstat*brand_share_3*B56*brand_cr_3 | C61: =wordstat*brand_share_3*C56*brand_cr_3 | D61: =wordstat*brand_share_3*D56*brand_cr_3 | E61: =wordstat*brand_share_3*E56*brand_cr_3 | F61: =wordstat*brand_share_3*F56*brand_cr_3 | G61: =wordstat*brand_share_3*G56*brand_cr_3 | H61: =wordstat*brand_share_3*H56*brand_cr_3 | I61: =wordstat*brand_share_3*I56*brand_cr_3 | ... Y61: =wordstat*brand_share_3*Y56*brand_cr_3
A62: Заказы сайта: соцсети и Telegram | B62: =followers*social_cr_3*B56 | C62: =followers*social_cr_3*C56 | D62: =followers*social_cr_3*D56 | E62: =followers*social_cr_3*E56 | F62: =followers*social_cr_3*F56 | G62: =followers*social_cr_3*G56 | H62: =followers*social_cr_3*H56 | I62: =followers*social_cr_3*I56 | ... Y62: =followers*social_cr_3*Y56
A63: Заказы сайта: Директ / VK | B63: =ads_budget_3/cpc_3*ads_cr_3*(0.5+0.5*B56) | C63: =ads_budget_3/cpc_3*ads_cr_3*(0.5+0.5*C56) | D63: =ads_budget_3/cpc_3*ads_cr_3*(0.5+0.5*D56) | E63: =ads_budget_3/cpc_3*ads_cr_3*(0.5+0.5*E56) | F63: =ads_budget_3/cpc_3*ads_cr_3*(0.5+0.5*F56) | G63: =ads_budget_3/cpc_3*ads_cr_3*(0.5+0.5*G56) | H63: =ads_budget_3/cpc_3*ads_cr_3*(0.5+0.5*H56) | I63: =ads_budget_3/cpc_3*ads_cr_3*(0.5+0.5*I56) | ... Y63: =ads_budget_3/cpc_3*ads_cr_3*(0.5+0.5*Y56)
A64: Заказов на сайте всего | B64: =B60+B61+B62+B63 | C64: =C60+C61+C62+C63 | D64: =D60+D61+D62+D63 | E64: =E60+E61+E62+E63 | F64: =F60+F61+F62+F63 | G64: =G60+G61+G62+G63 | H64: =H60+H61+H62+H63 | I64: =I60+I61+I62+I63 | ... Y64: =Y60+Y61+Y62+Y63
A65: Средний чек сайта, ₽ | B65: =mp_aov*aov_k_3 | C65: =mp_aov*aov_k_3 | D65: =mp_aov*aov_k_3 | E65: =mp_aov*aov_k_3 | F65: =mp_aov*aov_k_3 | G65: =mp_aov*aov_k_3 | H65: =mp_aov*aov_k_3 | I65: =mp_aov*aov_k_3 | ... Y65: =mp_aov*aov_k_3
A66: Выручка сайта, ₽ | B66: =B64*B65 | C66: =C64*C65 | D66: =D64*D65 | E66: =E64*E65 | F66: =F64*F65 | G66: =G64*G65 | H66: =H64*H65 | I66: =I64*I65 | ... Y66: =Y64*Y65
A67: в т.ч. новые деньги (прирост оборота), ₽ | B67: =B66*incr_3 | C67: =C66*incr_3 | D67: =D66*incr_3 | E67: =E66*incr_3 | F67: =F66*incr_3 | G67: =G66*incr_3 | H67: =H66*incr_3 | I67: =I66*incr_3 | ... Y67: =Y66*incr_3
A68: в т.ч. перешло с МП, ₽ | B68: =B66-B67 | C68: =C66-C67 | D68: =D66-D67 | E68: =E66-E67 | F68: =F66-F67 | G68: =G66-G67 | H68: =H66-H67 | I68: =I66-I67 | ... Y68: =Y66-Y67
A69: Доля сайта в общем обороте | B69: =B66/(mp_rev-B68+B66) | C69: =C66/(mp_rev-C68+C66) | D69: =D66/(mp_rev-D68+D66) | E69: =E66/(mp_rev-E68+E66) | F69: =F66/(mp_rev-F68+F66) | G69: =G66/(mp_rev-G68+G66) | H69: =H66/(mp_rev-H68+H66) | I69: =I66/(mp_rev-I68+I66) | ... Y69: =Y66/(mp_rev-Y68+Y66)
A70: Расходы сайта (без себестоимости), ₽ | B70: =B66*acq+B64*(ship+pick)+B60*B65*crm_pct+B61*B65*brand_cost+ads_budget_3+platform | C70: =C66*acq+C64*(ship+pick)+C60*C65*crm_pct+C61*C65*brand_cost+ads_budget_3+platform | D70: =D66*acq+D64*(ship+pick)+D60*D65*crm_pct+D61*D65*brand_cost+ads_budget_3+platform | E70: =E66*acq+E64*(ship+pick)+E60*E65*crm_pct+E61*E65*brand_cost+ads_budget_3+platform | F70: =F66*acq+F64*(ship+pick)+F60*F65*crm_pct+F61*F65*brand_cost+ads_budget_3+platform | G70: =G66*acq+G64*(ship+pick)+G60*G65*crm_pct+G61*G65*brand_cost+ads_budget_3+platform | H70: =H66*acq+H64*(ship+pick)+H60*H65*crm_pct+H61*H65*brand_cost+ads_budget_3+platform | I70: =I66*acq+I64*(ship+pick)+I60*I65*crm_pct+I61*I65*brand_cost+ads_budget_3+platform | ... Y70: =Y66*acq+Y64*(ship+pick)+Y60*Y65*crm_pct+Y61*Y65*brand_cost+ads_budget_3+platform
A71: Расходы сайта, % выручки | B71: =IF(B66=0,0,B70/B66) | C71: =IF(C66=0,0,C70/C66) | D71: =IF(D66=0,0,D70/D66) | E71: =IF(E66=0,0,E70/E66) | F71: =IF(F66=0,0,F70/F66) | G71: =IF(G66=0,0,G70/G66) | H71: =IF(H66=0,0,H70/H66) | I71: =IF(I66=0,0,I70/I66) | ... Y71: =IF(Y66=0,0,Y70/Y66)
A72: Наши услуги, ₽ | B72: =svc_setup+svc_month+B66*svc_pct | C72: =svc_month+C66*svc_pct | D72: =svc_month+D66*svc_pct | E72: =svc_month+E66*svc_pct | F72: =svc_month+F66*svc_pct | G72: =svc_month+G66*svc_pct | H72: =svc_month+H66*svc_pct | I72: =svc_month+I66*svc_pct | J72: =svc_month+J66*svc_pct | ... Y72: =svc_month+Y66*svc_pct
A73: Маржа сайта после себестоимости и расходов, ₽ | B73: =B66*(1-cogs)-B70-B72 | C73: =C66*(1-cogs)-C70-C72 | D73: =D66*(1-cogs)-D70-D72 | E73: =E66*(1-cogs)-E70-E72 | F73: =F66*(1-cogs)-F70-F72 | G73: =G66*(1-cogs)-G70-G72 | H73: =H66*(1-cogs)-H70-H72 | I73: =I66*(1-cogs)-I70-I72 | ... Y73: =Y66*(1-cogs)-Y70-Y72
A74: Маржа, которую эти заказы дали бы на МП, ₽ | B74: =B68*(1-cogs-mp_take) | C74: =C68*(1-cogs-mp_take) | D74: =D68*(1-cogs-mp_take) | E74: =E68*(1-cogs-mp_take) | F74: =F68*(1-cogs-mp_take) | G74: =G68*(1-cogs-mp_take) | H74: =H68*(1-cogs-mp_take) | I74: =I68*(1-cogs-mp_take) | ... Y74: =Y68*(1-cogs-mp_take)
A75: Чистый эффект для селлера, ₽ | B75: =B73-B74 | C75: =C73-C74 | D75: =D73-D74 | E75: =E73-E74 | F75: =F73-F74 | G75: =G73-G74 | H75: =H73-H74 | I75: =I73-I74 | ... Y75: =Y73-Y74
A76: Нарастающим итогом, ₽ | B76: =B75 | C76: =B76+C75 | D76: =C76+D75 | E76: =D76+E75 | F76: =E76+F75 | G76: =F76+G75 | H76: =G76+H75 | I76: =H76+I75 | J76: =I76+J75 | ... Y76: =X76+Y75
A77: Окупилось (1 = да) | B77: =IF(B76>0,1,0) | C77: =IF(C76>0,1,0) | D77: =IF(D76>0,1,0) | E77: =IF(E76>0,1,0) | F77: =IF(F76>0,1,0) | G77: =IF(G76>0,1,0) | H77: =IF(H76>0,1,0) | I77: =IF(I76>0,1,0) | ... Y77: =IF(Y76>0,1,0)

Sheet Справка
A1: Рыночные цифры для разговора (проверены на 06.10.2026)
A3: Цифра | B3: Значение | C3: Тип | D3: Источник
A4: Доля выручки, которую удерживают WB/Ozon/ЯМ | B4: 20% → 42% за 1,5 года | C4: оценка | D4: Финансист, RB.ru 25.09.2026
A5: Рост комиссий 2023–2025 | B5: WB +58%, Ozon +63% | C5: оценка | D5: АПЭТ/Mpstats, Коммерсант 19.02.2026
A6: Рентабельность селлеров | B6: 15% → 5%, к декабрю около 3% | C6: оценка | D6: Market Papa, Коммерсант 26.08.2026
A7: Комиссия Ozon с 06.04.2026 | B7: до 55%, одежда 43–48% | C7: факт | D7: Ведомости 03.02.2026
A8: Комиссия WB с 07.07.2026 | B8: +5 п.п. склад WB, +6 FBS, +20 витрина | C8: факт | D8: Коммерсант 07.07.2026
A9: Срок выплат WB | B9: около месяца, досрочно −4% | C9: факт | D9: Коммерсант 02.04.2026
A10: Атакованные склады WB, лето 2026 | B10: 17–22% площадей | C10: оценка | D10: Forbes / mail.ru
A11: Первые выплаты WB за потерянный товар | B11: 5–10% себестоимости | C11: факт | D11: vbr.ru 24.07.2026
A12: Полная компенсация WB | B12: только при ущербе до 500 тыс. ₽ | C12: факт | D12: msk1.ru 18.09.2026
A13: Рост независимого e-com в 2026 | B13: +25,8% против около +10% у МП | C13: факт (прогноз) | D13: INFOLine, Коммерсант 01.10.2026
A14: Селлеры WB, рассматривающие свой сайт | B14: 41,9% | C14: факт по пересказам | D14: Forbes, опрос 1–3.08.2026
... A26: Адрес своего сайта в чате WB | B26: разрешён (Telegram и соцсети — нет, штраф 25 000 ₽) | C26: факт | D26: Перечень штрафов WB, п. 8
